android_text_tool/__init__.py
android_text_tool/__main__.py
android_text_tool/main.py
android_text_tool/parser.py
android_text_tool/serializer.py
android_text_tool/serializer_csv.py
android_text_tool/serializer_dinodyct.py
android_text_tool/serializer_yaml.py
android_text_tool/serializers.py
android_text_tool/translarions_storage.py
android_text_tool/translation_key.py
android_text_tool/utils.py
android_text_tool-0.1.2.dist-info/LICENSE
android_text_tool-0.1.2.dist-info/METADATA
android_text_tool-0.1.2.dist-info/WHEEL
android_text_tool-0.1.2.dist-info/entry_points.txt
android_text_tool-0.1.2.dist-info/RECORD
