Metadata-Version: 2.1
Name: android-text-tool
Version: 0.1.2
Summary: This is a tool for extracting string resources from an Android project.
License: MIT
Author: Ihor Rusin
Author-email: phoenix.ria@gmail.com
Requires-Python: >=3.11,<4.0
Classifier: License :: OSI Approved :: MIT License
Classifier: Programming Language :: Python :: 3
Classifier: Programming Language :: Python :: 3.11
Requires-Dist: PyYAML (>=6.0.1,<7.0.0)
